hyperlink_extractor/__init__.py
hyperlink_extractor/extract.py
hyperlink_extractor-0.1.dist-info/METADATA
hyperlink_extractor-0.1.dist-info/RECORD
hyperlink_extractor-0.1.dist-info/WHEEL
hyperlink_extractor-0.1.dist-info/top_level.txt
